{
  "attempt": 1,
  "error": null,
  "raw_response": "[\n  {\n    \"type\": \"mcq_single\",\n    \"prompt\": \"Какой вариант правильно описывает постоянное место жительства?\",\n    \"choices\": [\n      {\n        \"id\": \"a\",\n        \"text\": \"I'm living in London.\"\n      },\n      {\n        \"id\": \"b\",\n        \"text\": \"I live in London.\"\n      },\n      {\n        \"id\": \"c\",\n        \"text\": \"I have lived in London.\"\n      },\n      {\n        \"id\": \"d\",\n        \"text\": \"I was living in London.\"\n      }\n    ],\n    \"correct_answer\": \"b\",\n    \"explanation\": \"Постоянное место жительства описывается Present Simple, поэтому правильный вариант — \\\"I live in London.\\\"\",\n    \"theory_block_id\": \"b5_theory_temporary_vs_permanent\",\n    \"chapter_id\": \"en.grammar.now_present_continuous_contrast.meanings_right_now_temporary\",\n    \"concept_id\": \"present_continuous_temporary_vs_permanent\",\n    \"difficulty\": 2\n  },\n  {\n    \"type\": \"mcq_single\",\n    \"prompt\": \"Какой вариант правильно описывает постоянную работу?\",\n    \"choices\": [\n      {\n        \"id\": \"a\",\n        \"text\": \"He's working at the company.\"\n      },\n      {\n        \"id\": \"b\",\n        \"text\": \"He works at the company.\"\n      },\n      {\n        \"id\": \"c\",\n        \"text\": \"He is working at the company.\"\n      },\n      {\n        \"id\": \"d\",\n        \"text\": \"He worked at the company.\"\n      }\n    ],\n    \"correct_answer\": \"b\",\n    \"explanation\": \"Постоянная работа описывается Present Simple, поэтому правильный вариант — \\\"He works at the company.\\\"\",\n    \"theory_block_id\": \"b5_theory_temporary_vs_permanent\",\n    \"chapter_id\": \"en.grammar.now_present_continuous_contrast.meanings_right_now_temporary\",\n    \"concept_id\": \"present_continuous_temporary_vs_permanent\",\n    \"difficulty\": 2\n  },\n  {\n    \"type\": \"mcq_single\",\n    \"prompt\": \"Какой вариант правильно описывает временную работу на этот семестр?\",\n    \"choices\": [\n      {\n        \"id\": \"a\",\n        \"text\": \"She works as a teacher this semester.\"\n      },\n      {\n        \"id\": \"b\",\n        \"text\": \"She's working as a teacher this semester.\"\n      },\n      {\n        \"id\": \"c\",\n        \"text\": \"She was working as a teacher this semester.\"\n      },\n      {\n        \"id\": \"d\",\n        \"text\": \"She has worked as a teacher this semester.\"\n      }\n    ],\n    \"correct_answer\": \"b\",\n    \"explanation\": \"Временная работа требует Present Continuous, поэтому правильный вариант — \\\"She's working as a teacher this semester.\\\"\",\n    \"theory_block_id\": \"b5_theory_temporary_vs_permanent\",\n    \"chapter_id\": \"en.grammar.now_present_continuous_contrast.meanings_right_now_temporary\",\n    \"concept_id\": \"present_continuous_temporary_vs_permanent\",\n    \"difficulty\": 3\n  },\n  {\n    \"type\": \"mcq_single\",\n    \"prompt\": \"Какой вариант правильно описывает постоянную привычку?\",\n    \"choices\": [\n      {\n        \"id\": \"a\",\n        \"text\": \"She's eating breakfast every day.\"\n      },\n      {\n        \"id\": \"b\",\n        \"text\": \"She eats breakfast every day.\"\n      },\n      {\n        \"id\": \"c\",\n        \"text\": \"She is eating breakfast every day.\"\n      },\n      {\n        \"id\": \"d\",\n        \"text\": \"She ate breakfast every day.\"\n      }\n    ],\n    \"correct_answer\": \"b\",\n    \"explanation\": \"Постоянная привычка описывается Present Simple, поэтому правильный вариант — \\\"She eats breakfast every day.\\\"\",\n    \"theory_block_id\": \"b5_theory_temporary_vs_permanent\",\n    \"chapter_id\": \"en.grammar.now_present_continuous_contrast.meanings_right_now_temporary\",\n    \"concept_id\": \"present_continuous_temporary_vs_permanent\",\n    \"difficulty\": 2\n  },\n  {\n    \"type\": \"mcq_single\",\n    \"prompt\": \"Какой вариант правильно описывает временное пребывание в отеле на выходные?\",\n    \"choices\": [\n      {\n        \"id\": \"a\",\n        \"text\": \"We live in a hotel this weekend.\"\n      },\n      {\n        \"id\": \"b\",\n        \"text\": \"We are staying in a hotel this weekend.\"\n      },\n      {\n        \"id\": \"c\",\n        \"text\": \"We stay in a hotel this weekend.\"\n      },\n      {\n        \"id\": \"d\",\n        \"text\": \"We lived in a hotel this weekend.\"\n      }\n    ],\n    \"correct_answer\": \"b\",\n    \"explanation\": \"Временное пребывание требует Present Continuous, поэтому правильный вариант — \\\"We are staying in a hotel this weekend.\\\"\",\n    \"theory_block_id\": \"b5_theory_temporary_vs_permanent\",\n    \"chapter_id\": \"en.grammar.now_present_continuous_contrast.meanings_right_now_temporary\",\n    \"concept_id\": \"present_continuous_temporary_vs_permanent\",\n    \"difficulty\": 3\n  },\n  {\n    \"type\": \"mcq_single\",\n    \"prompt\": \"Какой вариант правильно описывает постоянный факт природы?\",\n    \"choices\": [\n      {\n        \"id\": \"a\",\n        \"text\": \"The sun is shining today.\"\n      },\n      {\n        \"id\": \"b\",\n        \"text\": \"The sun shines every day.\"\n      },\n      {\n        \"id\": \"c\",\n        \"text\": \"The sun is shining every day.\"\n      },\n      {\n        \"id\": \"d\",\n        \"text\": \"The sun shone every day.\"\n      }\n    ],\n    \"correct_answer\": \"b\",\n    \"explanation\": \"Постоянная природная истина описывается Present Simple, поэтому правильный вариант — \\\"The sun shines every day.\\\"\",\n    \"theory_block_id\": \"b5_theory_temporary_vs_permanent\",\n    \"chapter_id\": \"en.grammar.now_present_continuous_contrast.meanings_right_now_temporary\",\n    \"concept_id\": \"present_continuous_temporary_vs_permanent\",\n    \"difficulty\": 2\n  },\n  {\n    \"type\": \"mcq_single\",\n    \"prompt\": \"Какой вариант правильно описывает временное событие, происходящее сегодня вечером?\",\n    \"choices\": [\n      {\n        \"id\": \"a\",\n        \"text\": \"The concert is happening this evening.\"\n      },\n      {\n        \"id\": \"b\",\n        \"text\": \"The concert happens this evening.\"\n      },\n      {\n        \"id\": \"c\",\n        \"text\": \"The concert is happening every evening.\"\n      },\n      {\n        \"id\": \"d\",\n        \"text\": \"The concert happens every evening.\"\n      }\n    ],\n    \"correct_answer\": \"a\",\n    \"explanation\": \"Временное событие требует Present Continuous, поэтому правильный вариант — \\\"The concert is happening this evening.\\\"\",\n    \"theory_block_id\": \"b5_theory_temporary_vs_permanent\",\n    \"chapter_id\": \"en.grammar.now_present_continuous_contrast.meanings_right_now_temporary\",\n    \"concept_id\": \"present_continuous_temporary_vs_permanent\",\n    \"difficulty\": 3\n  },\n  {\n    \"type\": \"mcq_single\",\n    \"prompt\": \"Какой вариант правильно описывает временную учебную активность на этой неделе?\",\n    \"choices\": [\n      {\n        \"id\": \"a\",\n        \"text\": \"I study for my exam this week.\"\n      },\n      {\n        \"id\": \"b\",\n        \"text\": \"I'm studying for my exam this week.\"\n      },\n      {\n        \"id\": \"c\",\n        \"text\": \"I have been studying for my exam this week.\"\n      },\n      {\n        \"id\": \"d\",\n        \"text\": \"I studied for my exam this week.\"\n      }\n    ],\n    \"correct_answer\": \"b\",\n    \"explanation\": \"Временная активность требует Present Continuous, поэтому правильный вариант — \\\"I'm studying for my exam this week.\\\"\",\n    \"theory_block_id\": \"b5_theory_temporary_vs_permanent\",\n    \"chapter_id\": \"en.grammar.now_present_continuous_contrast.meanings_right_now_temporary\",\n    \"concept_id\": \"present_continuous_temporary_vs_permanent\",\n    \"difficulty\": 3\n  },\n  {\n    \"type\": \"mcq_single\",\n    \"prompt\": \"Какой вариант правильно описывает постоянное местоположение компании?\",\n    \"choices\": [\n      {\n        \"id\": \"a\",\n        \"text\": \"The company is located in London.\"\n      },\n      {\n        \"id\": \"b\",\n        \"text\": \"The company is being located in London.\"\n      },\n      {\n        \"id\": \"c\",\n        \"text\": \"The company was located in London.\"\n      },\n      {\n        \"id\": \"d\",\n        \"text\": \"The company has been located in London.\"\n      }\n    ],\n    \"correct_answer\": \"a\",\n    \"explanation\": \"Постоянное местоположение описывается Present Simple, поэтому правильный вариант — \\\"The company is located in London.\\\"\",\n    \"theory_block_id\": \"b5_theory_temporary_vs_permanent\",\n    \"chapter_id\": \"en.grammar.now_present_continuous_contrast.meanings_right_now_temporary\",\n    \"concept_id\": \"present_continuous_temporary_vs_permanent\",\n    \"difficulty\": 2\n  },\n  {\n    \"type\": \"mcq_single\",\n    \"prompt\": \"Какой вариант правильно описывает регулярное расписание автобуса?\",\n    \"choices\": [\n      {\n        \"id\": \"a\",\n        \"text\": \"The bus arrives at 8 AM every day.\"\n      },\n      {\n        \"id\": \"b\",\n        \"text\": \"The bus is arriving at 8 AM every day.\"\n      },\n      {\n        \"id\": \"c\",\n        \"text\": \"The bus arrives at 8 AM today.\"\n      },\n      {\n        \"id\": \"d\",\n        \"text\": \"The bus is arriving at 8 AM today.\"\n      }\n    ],\n    \"correct_answer\": \"a\",\n    \"explanation\": \"Постоянное расписание описывается Present Simple, поэтому правильный вариант — \\\"The bus arrives at 8 AM every day.\\\"\",\n    \"theory_block_id\": \"b5_theory_temporary_vs_permanent\",\n    \"chapter_id\": \"en.grammar.now_present_continuous_contrast.meanings_right_now_temporary\",\n    \"concept_id\": \"present_continuous_temporary_vs_permanent\",\n    \"difficulty\": 2\n  }\n]"
}