{
  "chapter_outline": {
    "chapter_id": "en.grammar.describing_precisely_adjectives_adverbs.comparatives_superlatives_irregulars",
    "section_id": "en.grammar.describing_precisely_adjectives_adverbs",
    "title": "Comparatives/superlatives + irregulars (better/best…)",
    "title_short": "Comparatives/superlatives",
    "description": "Сравнительная и превосходная степень прилагательных: базовые правила, орфография, irregular forms.",
    "level": "B1",
    "ui_language": "ru",
    "target_language": "en",
    "prerequisites": [
      "en.grammar.describing_precisely_adjectives_adverbs.adjective_order"
    ],
    "learning_objectives": [
      "Образовывать сравнительную и превосходную степени для коротких прилагательных",
      "Использовать more/most для длинных прилагательных",
      "Знать и применять irregular forms (good/better/best и др.)",
      "Строить сравнения с than и the + superlative"
    ],
    "estimated_minutes": 24,
    "theory_blocks": [
      {
        "id": "b1_short_adjectives",
        "concept_id": "comparative_short",
        "title": "Короткие прилагательные: -er/-est",
        "order": 1,
        "description": "Базовые формы short adjectives + spelling rules."
      },
      {
        "id": "b2_long_adjectives",
        "concept_id": "comparative_long",
        "title": "Длинные прилагательные: more/most",
        "order": 2,
        "description": "Когда использовать more/most и where possible alternatives."
      },
      {
        "id": "b3_irregulars",
        "concept_id": "comparative_irregulars",
        "title": "Irregular forms",
        "order": 3,
        "description": "good/better/best, bad/worse/worst, far/further/farthest, little/less/least."
      },
      {
        "id": "b4_than_the",
        "concept_id": "comparative_than_superlative_the",
        "title": "Than и the + superlative",
        "order": 4,
        "description": "Структуры сравнения и позиция the."
      },
      {
        "id": "b5_uses_and_mistakes",
        "concept_id": "comparative_common_mistakes",
        "title": "Частые ошибки и стиль",
        "order": 5,
        "description": "more better, the most happiest и т.п."
      }
    ],
    "concept_refs": [
      "comparative_short",
      "comparative_long",
      "comparative_irregulars",
      "comparative_than_superlative_the",
      "comparative_common_mistakes"
    ],
    "question_types_needed": [
      "mcq_single",
      "fill_blank",
      "error_spotting",
      "reorder",
      "true_false"
    ],
    "title_translations": {
      "ru": "Сравнительные/превосходные + исключения (better/best…)"
    }
  }
}
