{
  "chapter_input": {
    "section_id": "en.grammar.describing_precisely_adjectives_adverbs",
    "chapter_id": "en.grammar.describing_precisely_adjectives_adverbs.ed_vs_ing_adjectives",
    "title": "-ed vs -ing adjectives (bored/boring)",
    "title_short": "-ed vs -ing adjectives",
    "description": "bored/boring",
    "level": "B1",
    "order": 1006,
    "ui_language": "ru",
    "target_language": "en",
    "prerequisites": [
      "en.grammar.describing_precisely_adjectives_adverbs.adverb_placement"
    ]
  }
}