{
  "theory_block": {
    "id": "b2_theory_for_vs_since",
    "concept_id": "for_period_since_point",
    "content_md": "**for** используется с **периодом** (сколько времени), а **since** — с **точкой начала**.\n\nСравните: *for three weeks* (период) и *since Monday* (начальная точка). Оба варианта обычно стоят в конце предложения, но это не строгое правило.",
    "key_points": [
      "for + период (three weeks, a long time)",
      "since + точка начала (Monday, 2019, my birthday)",
      "Оба варианты описывают длительность до настоящего"
    ],
    "common_mistakes": [
      {
        "wrong": "I have lived here since two years.",
        "right": "I have lived here for two years.",
        "why": "Two years — это период, поэтому нужен for, а не since."
      },
      {
        "wrong": "He has worked here for 2019.",
        "right": "He has worked here since 2019.",
        "why": "2019 — точка начала, значит нужно since."
      }
    ],
    "examples": [
      {
        "id": "ex4",
        "text": "We have been friends for ten years.",
        "translation": "Мы дружим десять лет.",
        "tags": ["for", "duration"]
      },
      {
        "id": "ex5",
        "text": "He has studied English since 2020.",
        "translation": "Он изучает английский с 2020 года.",
        "tags": ["since", "start_point"]
      }
    ]
  }
}
