{
  "attempt": 1,
  "error": null,
  "raw_response": "[\n  {\n    \"type\": \"mcq_single\",\n    \"prompt\": \"Какой вопрос правильный для единственного числа: 'Есть ли ручка на столе?'\",\n    \"choices\": [\n      {\n        \"id\": \"a\",\n        \"text\": \"Is there a pen on the table?\"\n      },\n      {\n        \"id\": \"b\",\n        \"text\": \"Are there a pen on the table?\"\n      },\n      {\n        \"id\": \"c\",\n        \"text\": \"Is there pens on the table?\"\n      },\n      {\n        \"id\": \"d\",\n        \"text\": \"Are there pens on the table?\"\n      }\n    ],\n    \"correct_answer\": \"a\",\n    \"explanation\": \"Для единственного числа используется 'Is there', а не 'Are there'. 'A' указывает на единственное число.\",\n    \"theory_block_id\": \"b4_theory_there_questions\",\n    \"chapter_id\": \"en.grammar.talking_about_things_nouns.there_is_are_existence\",\n    \"concept_id\": \"there_questions\",\n    \"difficulty\": 1\n  },\n  {\n    \"type\": \"mcq_single\",\n    \"prompt\": \"Какой вопрос правильный для множественного числа: 'Есть ли книги на полке?'\",\n    \"choices\": [\n      {\n        \"id\": \"a\",\n        \"text\": \"Is there books on the shelf?\"\n      },\n      {\n        \"id\": \"b\",\n        \"text\": \"Are there books on the shelf?\"\n      },\n      {\n        \"id\": \"c\",\n        \"text\": \"Is there a book on the shelf?\"\n      },\n      {\n        \"id\": \"d\",\n        \"text\": \"Are there a book on the shelf?\"\n      }\n    ],\n    \"correct_answer\": \"b\",\n    \"explanation\": \"Для множественного числа используется 'Are there', а не 'Is there'. 'Books' — множественное число.\",\n    \"theory_block_id\": \"b4_theory_there_questions\",\n    \"chapter_id\": \"en.grammar.talking_about_things_nouns.there_is_are_existence\",\n    \"concept_id\": \"there_questions\",\n    \"difficulty\": 1\n  },\n  {\n    \"type\": \"mcq_single\",\n    \"prompt\": \"Какой вопрос правильный: 'Есть ли стулья в комнате?'\",\n    \"choices\": [\n      {\n        \"id\": \"a\",\n        \"text\": \"Is there chairs in the room?\"\n      },\n      {\n        \"id\": \"b\",\n        \"text\": \"Are there chairs in the room?\"\n      },\n      {\n        \"id\": \"c\",\n        \"text\": \"Is there any chairs in the room?\"\n      },\n      {\n        \"id\": \"d\",\n        \"text\": \"Are there any chair in the room?\"\n      }\n    ],\n    \"correct_answer\": \"b\",\n    \"explanation\": \"Для множественного числа требуется 'Are there'. 'Any' используется с множественным числом, но не с 'chair' (единственное число).\",\n    \"theory_block_id\": \"b4_theory_there_questions\",\n    \"chapter_id\": \"en.grammar.talking_about_things_nouns.there_is_are_existence\",\n    \"concept_id\": \"there_questions\",\n    \"difficulty\": 1\n  },\n  {\n    \"type\": \"mcq_single\",\n    \"prompt\": \"Какой вопрос правильный: 'Есть ли ручка?'\",\n    \"choices\": [\n      {\n        \"id\": \"a\",\n        \"text\": \"Is there a pen?\"\n      },\n      {\n        \"id\": \"b\",\n        \"text\": \"Is there any pen?\"\n      },\n      {\n        \"id\": \"c\",\n        \"text\": \"Are there a pen?\"\n      },\n      {\n        \"id\": \"d\",\n        \"text\": \"Are there pens?\"\n      }\n    ],\n    \"correct_answer\": \"a\",\n    \"explanation\": \"Для единственного числа используется 'Is there a', а не 'any'. 'Any' применяется только для множественного числа.\",\n    \"theory_block_id\": \"b4_theory_there_questions\",\n    \"chapter_id\": \"en.grammar.talking_about_things_nouns.there_is_are_existence\",\n    \"concept_id\": \"there_questions\",\n    \"difficulty\": 1\n  },\n  {\n    \"type\": \"mcq_single\",\n    \"prompt\": \"Какой вопрос правильный для множественного числа: 'Есть ли карандаши на столе?'\",\n    \"choices\": [\n      {\n        \"id\": \"a\",\n        \"text\": \"Is there pencils on the table?\"\n      },\n      {\n        \"id\": \"b\",\n        \"text\": \"Are there pencils on the table?\"\n      },\n      {\n        \"id\": \"c\",\n        \"text\": \"Is there any pencils on the table?\"\n      },\n      {\n        \"id\": \"d\",\n        \"text\": \"Are there any pencil on the table?\"\n      }\n    ],\n    \"correct_answer\": \"b\",\n    \"explanation\": \"Для множественного числа требуется 'Are there'. 'Any' используется с множественным числом, но 'pencil' должно быть во множественном числе ('pencils').\",\n    \"theory_block_id\": \"b4_theory_there_questions\",\n    \"chapter_id\": \"en.grammar.talking_about_things_nouns.there_is_are_existence\",\n    \"concept_id\": \"there_questions\",\n    \"difficulty\": 1\n  },\n  {\n    \"type\": \"mcq_single\",\n    \"prompt\": \"Какой вопрос правильный: 'Есть ли кошка в комнате?'\",\n    \"choices\": [\n      {\n        \"id\": \"a\",\n        \"text\": \"Is there a cat in the room?\"\n      },\n      {\n        \"id\": \"b\",\n        \"text\": \"Are there a cat in the room?\"\n      },\n      {\n        \"id\": \"c\",\n        \"text\": \"Is there cats in the room?\"\n      },\n      {\n        \"id\": \"d\",\n        \"text\": \"Are there cats in the room?\"\n      }\n    ],\n    \"correct_answer\": \"a\",\n    \"explanation\": \"Для единственного числа используется 'Is there a', а не 'Are there'. 'Cats' — множественное число, поэтому 'Are there' неправильно.\",\n    \"theory_block_id\": \"b4_theory_there_questions\",\n    \"chapter_id\": \"en.grammar.talking_about_things_nouns.there_is_are_existence\",\n    \"concept_id\": \"there_questions\",\n    \"difficulty\": 1\n  },\n  {\n    \"type\": \"mcq_single\",\n    \"prompt\": \"Какой вопрос правильный для множественного числа: 'Есть ли стулья в классе?'\",\n    \"choices\": [\n      {\n        \"id\": \"a\",\n        \"text\": \"Is there chairs in the classroom?\"\n      },\n      {\n        \"id\": \"b\",\n        \"text\": \"Are there chairs in the classroom?\"\n      },\n      {\n        \"id\": \"c\",\n        \"text\": \"Is there any chairs in the classroom?\"\n      },\n      {\n        \"id\": \"d\",\n        \"text\": \"Are there any chair in the classroom?\"\n      }\n    ],\n    \"correct_answer\": \"b\",\n    \"explanation\": \"Для множественного числа требуется 'Are there'. 'Any' не используется с единственным числом ('chair').\",\n    \"theory_block_id\": \"b4_theory_there_questions\",\n    \"chapter_id\": \"en.grammar.talking_about_things_nouns.there_is_are_existence\",\n    \"concept_id\": \"there_questions\",\n    \"difficulty\": 1\n  },\n  {\n    \"type\": \"mcq_single\",\n    \"prompt\": \"Какой вопрос правильный: 'Есть ли яблоки на столе?'\",\n    \"choices\": [\n      {\n        \"id\": \"a\",\n        \"text\": \"Is there apples on the table?\"\n      },\n      {\n        \"id\": \"b\",\n        \"text\": \"Are there apples on the table?\"\n      },\n      {\n        \"id\": \"c\",\n        \"text\": \"Is there any apples on the table?\"\n      },\n      {\n        \"id\": \"d\",\n        \"text\": \"Are there any apple on the table?\"\n      }\n    ],\n    \"correct_answer\": \"b\",\n    \"explanation\": \"Для множественного числа используется 'Are there'. 'Any' не используется с 'apple' (единственное число).\",\n    \"theory_block_id\": \"b4_theory_there_questions\",\n    \"chapter_id\": \"en.grammar.talking_about_things_nouns.there_is_are_existence\",\n    \"concept_id\": \"there_questions\",\n    \"difficulty\": 1\n  },\n  {\n    \"type\": \"mcq_single\",\n    \"prompt\": \"Какой вопрос правильный для единственного числа: 'Есть ли стол в комнате?'\",\n    \"choices\": [\n      {\n        \"id\": \"a\",\n        \"text\": \"Is there a table in the room?\"\n      },\n      {\n        \"id\": \"b\",\n        \"text\": \"Are there a table in the room?\"\n      },\n      {\n        \"id\": \"c\",\n        \"text\": \"Is there tables in the room?\"\n      },\n      {\n        \"id\": \"d\",\n        \"text\": \"Are there tables in the room?\"\n      }\n    ],\n    \"correct_answer\": \"a\",\n    \"explanation\": \"Для единственного числа требуется 'Is there a', а не 'Are there'. 'Tables' — множественное число.\",\n    \"theory_block_id\": \"b4_theory_there_questions\",\n    \"chapter_id\": \"en.grammar.talking_about_things_nouns.there_is_are_existence\",\n    \"concept_id\": \"there_questions\",\n    \"difficulty\": 1\n  },\n  {\n    \"type\": \"mcq_single\",\n    \"prompt\": \"Какой вопрос правильный: 'Есть ли цветы на окне?'\",\n    \"choices\": [\n      {\n        \"id\": \"a\",\n        \"text\": \"Is there flowers on the window?\"\n      },\n      {\n        \"id\": \"b\",\n        \"text\": \"Are there flowers on the window?\"\n      },\n      {\n        \"id\": \"c\",\n        \"text\": \"Is there any flowers on the window?\"\n      },\n      {\n        \"id\": \"d\",\n        \"text\": \"Are there any flower on the window?\"\n      }\n    ],\n    \"correct_answer\": \"b\",\n    \"explanation\": \"Для множественного числа используется 'Are there'. 'Any' не применяется с 'flower' (единственное число).\",\n    \"theory_block_id\": \"b4_theory_there_questions\",\n    \"chapter_id\": \"en.grammar.talking_about_things_nouns.there_is_are_existence\",\n    \"concept_id\": \"there_questions\",\n    \"difficulty\": 1\n  }\n]"
}