{
  "theory_block": {
    "id": "b4_theory_perfect_participle",
    "concept_id": "perfect_participle_clauses",
    "content_md": "Perfect participle (**having + V3**) показывает, что действие произошло **раньше** основного. Это полезно, когда нужно подчеркнуть последовательность: *Having finished the report, she went home*.\\n\\nЕсли порядок действий очевиден, можно использовать обычный V-ing, но **having + V3** делает тайминг прозрачнее.",
    "examples": [
      {
        "id": "ex1",
        "text": "Having completed the course, he applied for a new job.",
        "translation": "Закончив курс, он подал на новую работу.",
        "tags": ["affirmative"]
      }
    ]
  }
}
