{
  "theory_block": {
    "id": "b5_theory_switching_practice",
    "concept_id": "mode_switching_practice",
    "content_md": "Теперь вы знаете, как «переключаться» между тремя режимами предложения. Одна идея — три способа её выразить.\n\n**Практический пример:**\n- Утверждение: \"He speaks English\"\n- Вопрос: \"Does he speak English?\"\n- Отрицание: \"He doesn't speak English\"\n\nВсе три предложения говорят об одной и той же идее — умении говорить по-английски. Разница только в том, как мы её выражаем: как факт, как вопрос или как отрицание.\n\nКогда вы видите любое английское предложение, подумайте: как оно будет выглядеть в других режимах? Это поможет лучше понять структуру английского языка.",
    "examples": [
      {
        "id": "ex1",
        "text": "He speaks English. → Does he speak English? → He doesn't speak English.",
        "translation": "Он говорит по-английски. → Он говорит по-английски? → Он не говорит по-английски.",
        "tags": ["statement", "question", "negative"]
      }
    ],
    "key_points": [
      "Одно предложение может быть утверждением, вопросом или отрицанием",
      "Это три «переключателя» одной и той же идеи",
      "Вопросы требуют изменения порядка слов (вспомогательный глагол в начале)",
      "Отрицания требуют добавления not после вспомогательного глагола"
    ]
  }
}
