{
  "theory_block": {
    "id": "b2_theory_forms_table",
    "concept_id": "object_pronouns_forms",
    "content_md": "В английском языке есть семь объектных местоимений. Каждое соответствует своему субъектному местоимению:\n\n**Единственное число:**\n- **I** → **me** (я → меня/мне)\n- **you** → **you** (ты/вы → тебя/вас)\n- **he** → **him** (он → его/ему)\n- **she** → **her** (она → её/ей)\n- **it** → **it** (оно → его/ему)\n\n**Множественное число:**\n- **we** → **us** (мы → нас/нам)\n- **they** → **them** (они → их/им)\n\nОбратите внимание: **you** и **it** одинаковы в субъектной и объектной форме. Остальные меняются: I → me, he → him, she → her, we → us, they → them.",
    "key_points": [
      "I → me, he → him, she → her, we → us, they → them",
      "you и it не меняются (you/you, it/it)",
      "Всего семь объектных местоимений"
    ],
    "examples": [
      {
        "id": "ex1",
        "text": "I see you.",
        "translation": "Я вижу тебя.",
        "notes": "you одинаково для субъекта и объекта",
        "tags": ["you"]
      },
      {
        "id": "ex2",
        "text": "She calls him.",
        "translation": "Она звонит ему.",
        "notes": "he (субъект) → him (объект)",
        "tags": ["he_him"]
      },
      {
        "id": "ex3",
        "text": "They help us.",
        "translation": "Они помогают нам.",
        "notes": "we (субъект) → us (объект)",
        "tags": ["we_us"]
      }
    ]
  }
}
