{
  "attempt": 1,
  "error": null,
  "raw_response": "[\n  {\n    \"type\": \"mcq_single\",\n    \"prompt\": \"Какой фразовый глагол является неразрывным?\",\n    \"choices\": [\n      {\n        \"id\": \"a\",\n        \"text\": \"pick up\"\n      },\n      {\n        \"id\": \"b\",\n        \"text\": \"turn off\"\n      },\n      {\n        \"id\": \"c\",\n        \"text\": \"look after\"\n      },\n      {\n        \"id\": \"d\",\n        \"text\": \"give up\"\n      }\n    ],\n    \"correct_answer\": \"c\",\n    \"explanation\": \"Глагол 'look after' является неразрывным, поэтому его нельзя разделять с объектом (например, 'look after her' — правильно, 'look her after' — неправильно).\",\n    \"theory_block_id\": \"b1_phrasal_what_is\",\n    \"chapter_id\": \"en.grammar.prepositions_verb_patterns.phrasal_verbs_as_grammar\",\n    \"concept_id\": \"phrasal_basics\",\n    \"difficulty\": 2\n  },\n  {\n    \"type\": \"mcq_single\",\n    \"prompt\": \"Какая фраза правильно использует неразрывный фразовый глагол?\",\n    \"choices\": [\n      {\n        \"id\": \"a\",\n        \"text\": \"She looked up her friend.\"\n      },\n      {\n        \"id\": \"b\",\n        \"text\": \"He picked up the book.\"\n      },\n      {\n        \"id\": \"c\",\n        \"text\": \"They looked after the children.\"\n      },\n      {\n        \"id\": \"d\",\n        \"text\": \"We turned off the TV.\"\n      }\n    ],\n    \"correct_answer\": \"c\",\n    \"explanation\": \"Глагол 'look after' неразрывный, поэтому правильная форма — 'looked after the children'. Остальные варианты используют разрывные глаголы.\",\n    \"theory_block_id\": \"b1_phrasal_what_is\",\n    \"chapter_id\": \"en.grammar.prepositions_verb_patterns.phrasal_verbs_as_grammar\",\n    \"concept_id\": \"phrasal_basics\",\n    \"difficulty\": 2\n  },\n  {\n    \"type\": \"mcq_single\",\n    \"prompt\": \"Какой фразовый глагол не может быть разделен с объектом?\",\n    \"choices\": [\n      {\n        \"id\": \"a\",\n        \"text\": \"pick up\"\n      },\n      {\n        \"id\": \"b\",\n        \"text\": \"turn off\"\n      },\n      {\n        \"id\": \"c\",\n        \"text\": \"look after\"\n      },\n      {\n        \"id\": \"d\",\n        \"text\": \"give up\"\n      }\n    ],\n    \"correct_answer\": \"c\",\n    \"explanation\": \"Глагол 'look after' неразрывный, поэтому его нельзя разделить (например, 'look after her' — правильно, 'look her after' — неправильно).\",\n    \"theory_block_id\": \"b1_phrasal_what_is\",\n    \"chapter_id\": \"en.grammar.prepositions_verb_patterns.phrasal_verbs_as_grammar\",\n    \"concept_id\": \"phrasal_basics\",\n    \"difficulty\": 2\n  },\n  {\n    \"type\": \"mcq_single\",\n    \"prompt\": \"Выберите правильное предложение с неразрывным фразовым глаголом.\",\n    \"choices\": [\n      {\n        \"id\": \"a\",\n        \"text\": \"She looked her up.\"\n      },\n      {\n        \"id\": \"b\",\n        \"text\": \"He turned the light off.\"\n      },\n      {\n        \"id\": \"c\",\n        \"text\": \"They looked after the baby.\"\n      },\n      {\n        \"id\": \"d\",\n        \"text\": \"We got the problem over.\"\n      }\n    ],\n    \"correct_answer\": \"c\",\n    \"explanation\": \"Глагол 'look after' неразрывный, поэтому правильная форма — 'looked after the baby'. Вариант d неправильный, так как 'get over' неразрывный.\",\n    \"theory_block_id\": \"b1_phrasal_what_is\",\n    \"chapter_id\": \"en.grammar.prepositions_verb_patterns.phrasal_verbs_as_grammar\",\n    \"concept_id\": \"phrasal_basics\",\n    \"difficulty\": 2\n  },\n  {\n    \"type\": \"mcq_single\",\n    \"prompt\": \"Какой фразовый глагол является неразрывным?\",\n    \"choices\": [\n      {\n        \"id\": \"a\",\n        \"text\": \"pick up\"\n      },\n      {\n        \"id\": \"b\",\n        \"text\": \"turn off\"\n      },\n      {\n        \"id\": \"c\",\n        \"text\": \"get over\"\n      },\n      {\n        \"id\": \"d\",\n        \"text\": \"give up\"\n      }\n    ],\n    \"correct_answer\": \"c\",\n    \"explanation\": \"Глагол 'get over' неразрывный, поэтому его нельзя разделить (например, 'got over the problem' — правильно, 'got the problem over' — неправильно).\",\n    \"theory_block_id\": \"b1_phrasal_what_is\",\n    \"chapter_id\": \"en.grammar.prepositions_verb_patterns.phrasal_verbs_as_grammar\",\n    \"concept_id\": \"phrasal_basics\",\n    \"difficulty\": 3\n  },\n  {\n    \"type\": \"mcq_single\",\n    \"prompt\": \"Какое предложение правильно использует разрывной фразовый глагол?\",\n    \"choices\": [\n      {\n        \"id\": \"a\",\n        \"text\": \"She looked after her sister.\"\n      },\n      {\n        \"id\": \"b\",\n        \"text\": \"He picked the book up.\"\n      },\n      {\n        \"id\": \"c\",\n        \"text\": \"They looked the child after.\"\n      },\n      {\n        \"id\": \"d\",\n        \"text\": \"We got over the problem.\"\n      }\n    ],\n    \"correct_answer\": \"b\",\n    \"explanation\": \"Глагол 'pick up' разрывной, поэтому правильная форма — 'picked the book up'. Варианты a и d используют неразрывные глаголы, вариант c неправильный.\",\n    \"theory_block_id\": \"b1_phrasal_what_is\",\n    \"chapter_id\": \"en.grammar.prepositions_verb_patterns.phrasal_verbs_as_grammar\",\n    \"concept_id\": \"phrasal_basics\",\n    \"difficulty\": 2\n  },\n  {\n    \"type\": \"mcq_single\",\n    \"prompt\": \"Какой фразовый глагол является неразрывным?\",\n    \"choices\": [\n      {\n        \"id\": \"a\",\n        \"text\": \"pick up\"\n      },\n      {\n        \"id\": \"b\",\n        \"text\": \"turn off\"\n      },\n      {\n        \"id\": \"c\",\n        \"text\": \"take after\"\n      },\n      {\n        \"id\": \"d\",\n        \"text\": \"give up\"\n      }\n    ],\n    \"correct_answer\": \"c\",\n    \"explanation\": \"Глагол 'take after' неразрывный, поэтому его нельзя разделить (например, 'took after his father' — правильно, 'took his father after' — неправильно).\",\n    \"theory_block_id\": \"b1_phrasal_what_is\",\n    \"chapter_id\": \"en.grammar.prepositions_verb_patterns.phrasal_verbs_as_grammar\",\n    \"concept_id\": \"phrasal_basics\",\n    \"difficulty\": 3\n  },\n  {\n    \"type\": \"mcq_single\",\n    \"prompt\": \"Какое предложение правильно использует 'take after'?\",\n    \"choices\": [\n      {\n        \"id\": \"a\",\n        \"text\": \"He took after his father.\"\n      },\n      {\n        \"id\": \"b\",\n        \"text\": \"He took his father after.\"\n      },\n      {\n        \"id\": \"c\",\n        \"text\": \"He took up his father.\"\n      },\n      {\n        \"id\": \"d\",\n        \"text\": \"He took off his father.\"\n      }\n    ],\n    \"correct_answer\": \"a\",\n    \"explanation\": \"Глагол 'take after' неразрывный, поэтому правильная форма — 'took after his father'. Остальные варианты содержат ошибки в структуре.\",\n    \"theory_block_id\": \"b1_phrasal_what_is\",\n    \"chapter_id\": \"en.grammar.prepositions_verb_patterns.phrasal_verbs_as_grammar\",\n    \"concept_id\": \"phrasal_basics\",\n    \"difficulty\": 3\n  },\n  {\n    \"type\": \"mcq_single\",\n    \"prompt\": \"Какой фразовый глагол является неразрывным?\",\n    \"choices\": [\n      {\n        \"id\": \"a\",\n        \"text\": \"pick up\"\n      },\n      {\n        \"id\": \"b\",\n        \"text\": \"turn off\"\n      },\n      {\n        \"id\": \"c\",\n        \"text\": \"run into\"\n      },\n      {\n        \"id\": \"d\",\n        \"text\": \"give up\"\n      }\n    ],\n    \"correct_answer\": \"c\",\n    \"explanation\": \"Глагол 'run into' неразрывный, поэтому его нельзя разделить (например, 'ran into her friend' — правильно, 'ran her friend into' — неправильно).\",\n    \"theory_block_id\": \"b1_phrasal_what_is\",\n    \"chapter_id\": \"en.grammar.prepositions_verb_patterns.phrasal_verbs_as_grammar\",\n    \"concept_id\": \"phrasal_basics\",\n    \"difficulty\": 3\n  },\n  {\n    \"type\": \"mcq_single\",\n    \"prompt\": \"Какое предложение правильно использует 'run into'?\",\n    \"choices\": [\n      {\n        \"id\": \"a\",\n        \"text\": \"She ran into her friend.\"\n      },\n      {\n        \"id\": \"b\",\n        \"text\": \"She ran her friend into.\"\n      },\n      {\n        \"id\": \"c\",\n        \"text\": \"She ran up her friend.\"\n      },\n      {\n        \"id\": \"d\",\n        \"text\": \"She ran off her friend.\"\n      }\n    ],\n    \"correct_answer\": \"a\",\n    \"explanation\": \"Глагол 'run into' неразрывный, поэтому правильная форма — 'ran into her friend'. Остальные варианты содержат ошибки в структуре фразового глагола.\",\n    \"theory_block_id\": \"b1_phrasal_what_is\",\n    \"chapter_id\": \"en.grammar.prepositions_verb_patterns.phrasal_verbs_as_grammar\",\n    \"concept_id\": \"phrasal_basics\",\n    \"difficulty\": 3\n  }\n]"
}