{
  "theory_block": {
    "id": "b2_theory_when_while",
    "concept_id": "when_while_links",
    "content_md": "**When** часто вводит короткое событие в Past Simple, а **while** — длительный процесс в Past Continuous.\n\nСравните: *While I was cooking, the phone rang*; *I was cooking when the phone rang*.",
    "examples": [
      {
        "id": "ex1",
        "text": "While she was studying, her friend called.",
        "translation": "Пока она училась, ей позвонил друг.",
        "notes": "while + процесс",
        "tags": ["affirmative"]
      },
      {
        "id": "ex2",
        "text": "I was studying when the door opened.",
        "translation": "Я учился, когда дверь открылась.",
        "notes": "when + событие",
        "tags": ["affirmative"]
      }
    ]
  }
}
