{
  "theory_block": {
    "id": "b2_theory_future_perfect_result",
    "concept_id": "future_perfect_result_by_time",
    "content_md": "Future Perfect отвечает на вопрос: **что будет уже сделано к определенному моменту в будущем**. Мы смотрим вперед и фиксируем результат к дедлайну или к другому событию в будущем. Важно, что действие завершено до указанной точки, а не просто происходит тогда.",
    "examples": [
      {
        "id": "ex1",
        "text": "She will have moved to Berlin by the end of the year.",
        "translation": "К концу года она уже переедет в Берлин.",
        "tags": ["affirmative", "deadline"]
      },
      {
        "id": "ex2",
        "text": "They will not have signed the contract by Monday.",
        "translation": "К понедельнику они не успеют подписать контракт.",
        "tags": ["negative"]
      }
    ]
  }
}
