{
  "id": "free_en_a1_reading_1778501348",
  "category_id": "en_a1",
  "title": "Lily's Ball",
  "level": "A1",
  "target_language": "en",
  "reading_passage": {
    "title": "Lily's Ball",
    "level": "A1",
    "target_language": "en",
    "estimated_minutes": 6,
    "segments": [
      {
        "segment_id": "s1",
        "speaker_id": "narrator",
        "voice_id": "en_narrator",
        "text": "Lily plays with her red ball in the park.",
        "text_translation_ru": "Лили играет с красным мячом в парке.",
        "audio_rel_path": "assets/reading/free_en_a1_reading_1778501348/seg_01_narrator.mp3",
        "tokens": [
          {
            "surface": "Lily",
            "lemma": "lily",
            "clickable": true,
            "token_idx": 0
          },
          {
            "surface": "plays",
            "lemma": "plays",
            "clickable": true,
            "token_idx": 1
          },
          {
            "surface": "with",
            "lemma": "with",
            "clickable": true,
            "token_idx": 2
          },
          {
            "surface": "her",
            "lemma": "her",
            "clickable": true,
            "token_idx": 3
          },
          {
            "surface": "red",
            "lemma": "red",
            "clickable": true,
            "token_idx": 4
          },
          {
            "surface": "ball",
            "lemma": "ball",
            "clickable": true,
            "token_idx": 5
          },
          {
            "surface": "in",
            "lemma": "in",
            "clickable": true,
            "token_idx": 6
          },
          {
            "surface": "the",
            "lemma": "the",
            "clickable": true,
            "token_idx": 7
          },
          {
            "surface": "park",
            "lemma": "park",
            "clickable": true,
            "token_idx": 8
          },
          {
            "surface": ".",
            "lemma": ".",
            "clickable": false,
            "token_idx": 9
          }
        ]
      },
      {
        "segment_id": "s2",
        "speaker_id": "narrator",
        "voice_id": "en_narrator",
        "text": "It is sunny. The ball rolls under a bench.",
        "text_translation_ru": "Солнечно. Мяч покатился под скамейку.",
        "audio_rel_path": "assets/reading/free_en_a1_reading_1778501348/seg_02_narrator.mp3",
        "tokens": [
          {
            "surface": "It",
            "lemma": "it",
            "clickable": true,
            "token_idx": 0
          },
          {
            "surface": "is",
            "lemma": "is",
            "clickable": true,
            "token_idx": 1
          },
          {
            "surface": "sunny",
            "lemma": "sunny",
            "clickable": true,
            "token_idx": 2
          },
          {
            "surface": ".",
            "lemma": ".",
            "clickable": false,
            "token_idx": 3
          },
          {
            "surface": "The",
            "lemma": "the",
            "clickable": true,
            "token_idx": 4
          },
          {
            "surface": "ball",
            "lemma": "ball",
            "clickable": true,
            "token_idx": 5
          },
          {
            "surface": "rolls",
            "lemma": "rolls",
            "clickable": true,
            "token_idx": 6
          },
          {
            "surface": "under",
            "lemma": "under",
            "clickable": true,
            "token_idx": 7
          },
          {
            "surface": "a",
            "lemma": "a",
            "clickable": true,
            "token_idx": 8
          },
          {
            "surface": "bench",
            "lemma": "bench",
            "clickable": true,
            "token_idx": 9
          },
          {
            "surface": ".",
            "lemma": ".",
            "clickable": false,
            "token_idx": 10
          }
        ]
      },
      {
        "segment_id": "s3",
        "speaker_id": "narrator",
        "voice_id": "en_narrator",
        "text": "Lily looks under the bench but cannot see the ball.",
        "text_translation_ru": "Лили смотрит под скамейку, но не видит мяч.",
        "audio_rel_path": "assets/reading/free_en_a1_reading_1778501348/seg_03_narrator.mp3",
        "tokens": [
          {
            "surface": "Lily",
            "lemma": "lily",
            "clickable": true,
            "token_idx": 0
          },
          {
            "surface": "looks",
            "lemma": "looks",
            "clickable": true,
            "token_idx": 1
          },
          {
            "surface": "under",
            "lemma": "under",
            "clickable": true,
            "token_idx": 2
          },
          {
            "surface": "the",
            "lemma": "the",
            "clickable": true,
            "token_idx": 3
          },
          {
            "surface": "bench",
            "lemma": "bench",
            "clickable": true,
            "token_idx": 4
          },
          {
            "surface": "but",
            "lemma": "but",
            "clickable": true,
            "token_idx": 5
          },
          {
            "surface": "cannot",
            "lemma": "cannot",
            "clickable": true,
            "token_idx": 6
          },
          {
            "surface": "see",
            "lemma": "see",
            "clickable": true,
            "token_idx": 7
          },
          {
            "surface": "the",
            "lemma": "the",
            "clickable": true,
            "token_idx": 8
          },
          {
            "surface": "ball",
            "lemma": "ball",
            "clickable": true,
            "token_idx": 9
          },
          {
            "surface": ".",
            "lemma": ".",
            "clickable": false,
            "token_idx": 10
          }
        ]
      },
      {
        "segment_id": "s4",
        "speaker_id": "narrator",
        "voice_id": "en_narrator",
        "text": "Tom sees Lily and asks, 'Can I help?'",
        "text_translation_ru": "Том видит Лили и спрашивает: «Могу я помочь?»",
        "audio_rel_path": "assets/reading/free_en_a1_reading_1778501348/seg_04_narrator.mp3",
        "tokens": [
          {
            "surface": "Tom",
            "lemma": "tom",
            "clickable": true,
            "token_idx": 0
          },
          {
            "surface": "sees",
            "lemma": "sees",
            "clickable": true,
            "token_idx": 1
          },
          {
            "surface": "Lily",
            "lemma": "lily",
            "clickable": true,
            "token_idx": 2
          },
          {
            "surface": "and",
            "lemma": "and",
            "clickable": true,
            "token_idx": 3
          },
          {
            "surface": "asks",
            "lemma": "asks",
            "clickable": true,
            "token_idx": 4
          },
          {
            "surface": ",",
            "lemma": ",",
            "clickable": false,
            "token_idx": 5
          },
          {
            "surface": "'",
            "lemma": "'",
            "clickable": false,
            "token_idx": 6
          },
          {
            "surface": "Can",
            "lemma": "can",
            "clickable": true,
            "token_idx": 7
          },
          {
            "surface": "I",
            "lemma": "i",
            "clickable": true,
            "token_idx": 8
          },
          {
            "surface": "help",
            "lemma": "help",
            "clickable": true,
            "token_idx": 9
          },
          {
            "surface": "?",
            "lemma": "?",
            "clickable": false,
            "token_idx": 10
          },
          {
            "surface": "'",
            "lemma": "'",
            "clickable": false,
            "token_idx": 11
          }
        ]
      },
      {
        "segment_id": "s5",
        "speaker_id": "narrator",
        "voice_id": "en_narrator",
        "text": "Lily says, 'Yes, please!'",
        "text_translation_ru": "Лили говорит: «Да, пожалуйста!»",
        "audio_rel_path": "assets/reading/free_en_a1_reading_1778501348/seg_05_narrator.mp3",
        "tokens": [
          {
            "surface": "Lily",
            "lemma": "lily",
            "clickable": true,
            "token_idx": 0
          },
          {
            "surface": "says",
            "lemma": "says",
            "clickable": true,
            "token_idx": 1
          },
          {
            "surface": ",",
            "lemma": ",",
            "clickable": false,
            "token_idx": 2
          },
          {
            "surface": "'",
            "lemma": "'",
            "clickable": false,
            "token_idx": 3
          },
          {
            "surface": "Yes",
            "lemma": "yes",
            "clickable": true,
            "token_idx": 4
          },
          {
            "surface": ",",
            "lemma": ",",
            "clickable": false,
            "token_idx": 5
          },
          {
            "surface": "please",
            "lemma": "please",
            "clickable": true,
            "token_idx": 6
          },
          {
            "surface": "!",
            "lemma": "!",
            "clickable": false,
            "token_idx": 7
          },
          {
            "surface": "'",
            "lemma": "'",
            "clickable": false,
            "token_idx": 8
          }
        ]
      },
      {
        "segment_id": "s6",
        "speaker_id": "narrator",
        "voice_id": "en_narrator",
        "text": "Tom gets the ball and gives it to Lily.",
        "text_translation_ru": "Том достает мяч и дает его Лили.",
        "audio_rel_path": "assets/reading/free_en_a1_reading_1778501348/seg_06_narrator.mp3",
        "tokens": [
          {
            "surface": "Tom",
            "lemma": "tom",
            "clickable": true,
            "token_idx": 0
          },
          {
            "surface": "gets",
            "lemma": "gets",
            "clickable": true,
            "token_idx": 1
          },
          {
            "surface": "the",
            "lemma": "the",
            "clickable": true,
            "token_idx": 2
          },
          {
            "surface": "ball",
            "lemma": "ball",
            "clickable": true,
            "token_idx": 3
          },
          {
            "surface": "and",
            "lemma": "and",
            "clickable": true,
            "token_idx": 4
          },
          {
            "surface": "gives",
            "lemma": "gives",
            "clickable": true,
            "token_idx": 5
          },
          {
            "surface": "it",
            "lemma": "it",
            "clickable": true,
            "token_idx": 6
          },
          {
            "surface": "to",
            "lemma": "to",
            "clickable": true,
            "token_idx": 7
          },
          {
            "surface": "Lily",
            "lemma": "lily",
            "clickable": true,
            "token_idx": 8
          },
          {
            "surface": ".",
            "lemma": ".",
            "clickable": false,
            "token_idx": 9
          }
        ]
      },
      {
        "segment_id": "s7",
        "speaker_id": "narrator",
        "voice_id": "en_narrator",
        "text": "Lily says, 'Thank you, Tom!'",
        "text_translation_ru": "Лили говорит: «Спасибо, Том!»",
        "audio_rel_path": "assets/reading/free_en_a1_reading_1778501348/seg_07_narrator.mp3",
        "tokens": [
          {
            "surface": "Lily",
            "lemma": "lily",
            "clickable": true,
            "token_idx": 0
          },
          {
            "surface": "says",
            "lemma": "says",
            "clickable": true,
            "token_idx": 1
          },
          {
            "surface": ",",
            "lemma": ",",
            "clickable": false,
            "token_idx": 2
          },
          {
            "surface": "'",
            "lemma": "'",
            "clickable": false,
            "token_idx": 3
          },
          {
            "surface": "Thank",
            "lemma": "thank",
            "clickable": true,
            "token_idx": 4
          },
          {
            "surface": "you",
            "lemma": "you",
            "clickable": true,
            "token_idx": 5
          },
          {
            "surface": ",",
            "lemma": ",",
            "clickable": false,
            "token_idx": 6
          },
          {
            "surface": "Tom",
            "lemma": "tom",
            "clickable": true,
            "token_idx": 7
          },
          {
            "surface": "!",
            "lemma": "!",
            "clickable": false,
            "token_idx": 8
          },
          {
            "surface": "'",
            "lemma": "'",
            "clickable": false,
            "token_idx": 9
          }
        ]
      },
      {
        "segment_id": "s8",
        "speaker_id": "narrator",
        "voice_id": "en_narrator",
        "text": "Tom and Lily play with the ball.",
        "text_translation_ru": "Том и Лили играют с мячом.",
        "audio_rel_path": "assets/reading/free_en_a1_reading_1778501348/seg_08_narrator.mp3",
        "tokens": [
          {
            "surface": "Tom",
            "lemma": "tom",
            "clickable": true,
            "token_idx": 0
          },
          {
            "surface": "and",
            "lemma": "and",
            "clickable": true,
            "token_idx": 1
          },
          {
            "surface": "Lily",
            "lemma": "lily",
            "clickable": true,
            "token_idx": 2
          },
          {
            "surface": "play",
            "lemma": "play",
            "clickable": true,
            "token_idx": 3
          },
          {
            "surface": "with",
            "lemma": "with",
            "clickable": true,
            "token_idx": 4
          },
          {
            "surface": "the",
            "lemma": "the",
            "clickable": true,
            "token_idx": 5
          },
          {
            "surface": "ball",
            "lemma": "ball",
            "clickable": true,
            "token_idx": 6
          },
          {
            "surface": ".",
            "lemma": ".",
            "clickable": false,
            "token_idx": 7
          }
        ]
      }
    ],
    "vocab_focus": [
      "ball",
      "help",
      "thank"
    ],
    "comprehension_questions": [
      {
        "id": "q1",
        "prompt": "Lily plays with a blue ball.",
        "type": "true_false",
        "correct_answer": "false",
        "explanation": "The ball is red, not blue."
      },
      {
        "id": "q2",
        "prompt": "Tom helps Lily.",
        "type": "true_false",
        "correct_answer": "true",
        "explanation": "Tom gets the ball and gives it to Lily."
      },
      {
        "id": "q3",
        "prompt": "What does Lily say to Tom?",
        "type": "multiple_choice",
        "correct_answer": "a",
        "explanation": "Lily says 'Thank you, Tom!'"
      }
    ]
  }
}
