{
  "id": "free_en_b1_reading_1778503761",
  "category_id": "en_b1",
  "title": "A Market Souvenir",
  "level": "B1",
  "target_language": "en",
  "reading_passage": {
    "title": "A Market Souvenir",
    "level": "B1",
    "target_language": "en",
    "estimated_minutes": 6,
    "segments": [
      {
        "segment_id": "s1",
        "speaker_id": "narrator",
        "voice_id": "en_narrator",
        "text": "On a sunny Saturday morning, Anna entered the busy market in the old town.",
        "text_translation_ru": "В солнечное субботнее утро Анна вошла в оживленный рынок в старом городе.",
        "audio_rel_path": "assets/reading/free_en_b1_reading_1778503761/seg_01_narrator.mp3",
        "tokens": [
          {
            "surface": "On",
            "lemma": "on",
            "clickable": true,
            "token_idx": 0
          },
          {
            "surface": "a",
            "lemma": "a",
            "clickable": true,
            "token_idx": 1
          },
          {
            "surface": "sunny",
            "lemma": "sunny",
            "clickable": true,
            "token_idx": 2
          },
          {
            "surface": "Saturday",
            "lemma": "saturday",
            "clickable": true,
            "token_idx": 3
          },
          {
            "surface": "morning",
            "lemma": "morning",
            "clickable": true,
            "token_idx": 4
          },
          {
            "surface": ",",
            "lemma": ",",
            "clickable": false,
            "token_idx": 5
          },
          {
            "surface": "Anna",
            "lemma": "anna",
            "clickable": true,
            "token_idx": 6
          },
          {
            "surface": "entered",
            "lemma": "entered",
            "clickable": true,
            "token_idx": 7
          },
          {
            "surface": "the",
            "lemma": "the",
            "clickable": true,
            "token_idx": 8
          },
          {
            "surface": "busy",
            "lemma": "busy",
            "clickable": true,
            "token_idx": 9
          },
          {
            "surface": "market",
            "lemma": "market",
            "clickable": true,
            "token_idx": 10
          },
          {
            "surface": "in",
            "lemma": "in",
            "clickable": true,
            "token_idx": 11
          },
          {
            "surface": "the",
            "lemma": "the",
            "clickable": true,
            "token_idx": 12
          },
          {
            "surface": "old",
            "lemma": "old",
            "clickable": true,
            "token_idx": 13
          },
          {
            "surface": "town",
            "lemma": "town",
            "clickable": true,
            "token_idx": 14
          },
          {
            "surface": ".",
            "lemma": ".",
            "clickable": false,
            "token_idx": 15
          }
        ]
      },
      {
        "segment_id": "s2",
        "speaker_id": "narrator",
        "voice_id": "en_narrator",
        "text": "She was looking for a small souvenir to take home.",
        "text_translation_ru": "Она искала небольшой сувенир, чтобы взять домой.",
        "audio_rel_path": "assets/reading/free_en_b1_reading_1778503761/seg_02_narrator.mp3",
        "tokens": [
          {
            "surface": "She",
            "lemma": "she",
            "clickable": true,
            "token_idx": 0
          },
          {
            "surface": "was",
            "lemma": "was",
            "clickable": true,
            "token_idx": 1
          },
          {
            "surface": "looking",
            "lemma": "looking",
            "clickable": true,
            "token_idx": 2
          },
          {
            "surface": "for",
            "lemma": "for",
            "clickable": true,
            "token_idx": 3
          },
          {
            "surface": "a",
            "lemma": "a",
            "clickable": true,
            "token_idx": 4
          },
          {
            "surface": "small",
            "lemma": "small",
            "clickable": true,
            "token_idx": 5
          },
          {
            "surface": "souvenir",
            "lemma": "souvenir",
            "clickable": true,
            "token_idx": 6
          },
          {
            "surface": "to",
            "lemma": "to",
            "clickable": true,
            "token_idx": 7
          },
          {
            "surface": "take",
            "lemma": "take",
            "clickable": true,
            "token_idx": 8
          },
          {
            "surface": "home",
            "lemma": "home",
            "clickable": true,
            "token_idx": 9
          },
          {
            "surface": ".",
            "lemma": ".",
            "clickable": false,
            "token_idx": 10
          }
        ]
      },
      {
        "segment_id": "s3",
        "speaker_id": "narrator",
        "voice_id": "en_narrator",
        "text": "She stopped at a stall selling handmade pottery.",
        "text_translation_ru": "Она остановилась у лотка, продающего ручную керамику.",
        "audio_rel_path": "assets/reading/free_en_b1_reading_1778503761/seg_03_narrator.mp3",
        "tokens": [
          {
            "surface": "She",
            "lemma": "she",
            "clickable": true,
            "token_idx": 0
          },
          {
            "surface": "stopped",
            "lemma": "stopped",
            "clickable": true,
            "token_idx": 1
          },
          {
            "surface": "at",
            "lemma": "at",
            "clickable": true,
            "token_idx": 2
          },
          {
            "surface": "a",
            "lemma": "a",
            "clickable": true,
            "token_idx": 3
          },
          {
            "surface": "stall",
            "lemma": "stall",
            "clickable": true,
            "token_idx": 4
          },
          {
            "surface": "selling",
            "lemma": "selling",
            "clickable": true,
            "token_idx": 5
          },
          {
            "surface": "handmade",
            "lemma": "handmade",
            "clickable": true,
            "token_idx": 6
          },
          {
            "surface": "pottery",
            "lemma": "pottery",
            "clickable": true,
            "token_idx": 7
          },
          {
            "surface": ".",
            "lemma": ".",
            "clickable": false,
            "token_idx": 8
          }
        ]
      },
      {
        "segment_id": "s4",
        "speaker_id": "narrator",
        "voice_id": "en_narrator",
        "text": "A blue bowl caught her eye; it was beautiful.",
        "text_translation_ru": "Синяя миска привлекла ее внимание; она была прекрасной.",
        "audio_rel_path": "assets/reading/free_en_b1_reading_1778503761/seg_04_narrator.mp3",
        "tokens": [
          {
            "surface": "A",
            "lemma": "a",
            "clickable": true,
            "token_idx": 0
          },
          {
            "surface": "blue",
            "lemma": "blue",
            "clickable": true,
            "token_idx": 1
          },
          {
            "surface": "bowl",
            "lemma": "bowl",
            "clickable": true,
            "token_idx": 2
          },
          {
            "surface": "caught",
            "lemma": "caught",
            "clickable": true,
            "token_idx": 3
          },
          {
            "surface": "her",
            "lemma": "her",
            "clickable": true,
            "token_idx": 4
          },
          {
            "surface": "eye",
            "lemma": "eye",
            "clickable": true,
            "token_idx": 5
          },
          {
            "surface": ";",
            "lemma": ";",
            "clickable": false,
            "token_idx": 6
          },
          {
            "surface": "it",
            "lemma": "it",
            "clickable": true,
            "token_idx": 7
          },
          {
            "surface": "was",
            "lemma": "was",
            "clickable": true,
            "token_idx": 8
          },
          {
            "surface": "beautiful",
            "lemma": "beautiful",
            "clickable": true,
            "token_idx": 9
          },
          {
            "surface": ".",
            "lemma": ".",
            "clickable": false,
            "token_idx": 10
          }
        ]
      },
      {
        "segment_id": "s5",
        "speaker_id": "narrator",
        "voice_id": "en_narrator",
        "text": "The price was two euros, but Anna only had one euro coin.",
        "text_translation_ru": "Цена была два евро, но у Анны был только один евро-монет.",
        "audio_rel_path": "assets/reading/free_en_b1_reading_1778503761/seg_05_narrator.mp3",
        "tokens": [
          {
            "surface": "The",
            "lemma": "the",
            "clickable": true,
            "token_idx": 0
          },
          {
            "surface": "price",
            "lemma": "price",
            "clickable": true,
            "token_idx": 1
          },
          {
            "surface": "was",
            "lemma": "was",
            "clickable": true,
            "token_idx": 2
          },
          {
            "surface": "two",
            "lemma": "two",
            "clickable": true,
            "token_idx": 3
          },
          {
            "surface": "euros",
            "lemma": "euros",
            "clickable": true,
            "token_idx": 4
          },
          {
            "surface": ",",
            "lemma": ",",
            "clickable": false,
            "token_idx": 5
          },
          {
            "surface": "but",
            "lemma": "but",
            "clickable": true,
            "token_idx": 6
          },
          {
            "surface": "Anna",
            "lemma": "anna",
            "clickable": true,
            "token_idx": 7
          },
          {
            "surface": "only",
            "lemma": "only",
            "clickable": true,
            "token_idx": 8
          },
          {
            "surface": "had",
            "lemma": "had",
            "clickable": true,
            "token_idx": 9
          },
          {
            "surface": "one",
            "lemma": "one",
            "clickable": true,
            "token_idx": 10
          },
          {
            "surface": "euro",
            "lemma": "euro",
            "clickable": true,
            "token_idx": 11
          },
          {
            "surface": "coin",
            "lemma": "coin",
            "clickable": true,
            "token_idx": 12
          },
          {
            "surface": ".",
            "lemma": ".",
            "clickable": false,
            "token_idx": 13
          }
        ]
      },
      {
        "segment_id": "s6",
        "speaker_id": "narrator",
        "voice_id": "en_narrator",
        "text": "She felt a bit embarrassed and looked at the vendor.",
        "text_translation_ru": "Она почувствовала себя немного смущенной и посмотрела на продавца.",
        "audio_rel_path": "assets/reading/free_en_b1_reading_1778503761/seg_06_narrator.mp3",
        "tokens": [
          {
            "surface": "She",
            "lemma": "she",
            "clickable": true,
            "token_idx": 0
          },
          {
            "surface": "felt",
            "lemma": "felt",
            "clickable": true,
            "token_idx": 1
          },
          {
            "surface": "a",
            "lemma": "a",
            "clickable": true,
            "token_idx": 2
          },
          {
            "surface": "bit",
            "lemma": "bit",
            "clickable": true,
            "token_idx": 3
          },
          {
            "surface": "embarrassed",
            "lemma": "embarrassed",
            "clickable": true,
            "token_idx": 4
          },
          {
            "surface": "and",
            "lemma": "and",
            "clickable": true,
            "token_idx": 5
          },
          {
            "surface": "looked",
            "lemma": "looked",
            "clickable": true,
            "token_idx": 6
          },
          {
            "surface": "at",
            "lemma": "at",
            "clickable": true,
            "token_idx": 7
          },
          {
            "surface": "the",
            "lemma": "the",
            "clickable": true,
            "token_idx": 8
          },
          {
            "surface": "vendor",
            "lemma": "vendor",
            "clickable": true,
            "token_idx": 9
          },
          {
            "surface": ".",
            "lemma": ".",
            "clickable": false,
            "token_idx": 10
          }
        ]
      },
      {
        "segment_id": "s7",
        "speaker_id": "narrator",
        "voice_id": "en_narrator",
        "text": "The vendor, a smiling woman, said, 'I have small coins.'",
        "text_translation_ru": "Продавец, улыбающаяся женщина, сказала: «У меня есть мелкие монеты».",
        "audio_rel_path": "assets/reading/free_en_b1_reading_1778503761/seg_07_narrator.mp3",
        "tokens": [
          {
            "surface": "The",
            "lemma": "the",
            "clickable": true,
            "token_idx": 0
          },
          {
            "surface": "vendor",
            "lemma": "vendor",
            "clickable": true,
            "token_idx": 1
          },
          {
            "surface": ",",
            "lemma": ",",
            "clickable": false,
            "token_idx": 2
          },
          {
            "surface": "a",
            "lemma": "a",
            "clickable": true,
            "token_idx": 3
          },
          {
            "surface": "smiling",
            "lemma": "smiling",
            "clickable": true,
            "token_idx": 4
          },
          {
            "surface": "woman",
            "lemma": "woman",
            "clickable": true,
            "token_idx": 5
          },
          {
            "surface": ",",
            "lemma": ",",
            "clickable": false,
            "token_idx": 6
          },
          {
            "surface": "said",
            "lemma": "said",
            "clickable": true,
            "token_idx": 7
          },
          {
            "surface": ",",
            "lemma": ",",
            "clickable": false,
            "token_idx": 8
          },
          {
            "surface": "'",
            "lemma": "'",
            "clickable": false,
            "token_idx": 9
          },
          {
            "surface": "I",
            "lemma": "i",
            "clickable": true,
            "token_idx": 10
          },
          {
            "surface": "have",
            "lemma": "have",
            "clickable": true,
            "token_idx": 11
          },
          {
            "surface": "small",
            "lemma": "small",
            "clickable": true,
            "token_idx": 12
          },
          {
            "surface": "coins",
            "lemma": "coins",
            "clickable": true,
            "token_idx": 13
          },
          {
            "surface": ".",
            "lemma": ".",
            "clickable": false,
            "token_idx": 14
          },
          {
            "surface": "'",
            "lemma": "'",
            "clickable": false,
            "token_idx": 15
          }
        ]
      },
      {
        "segment_id": "s8",
        "speaker_id": "narrator",
        "voice_id": "en_narrator",
        "text": "She gave Anna the extra coin and a friendly smile.",
        "text_translation_ru": "Она дала Анне дополнительную монету и дружелюбную улыбку.",
        "audio_rel_path": "assets/reading/free_en_b1_reading_1778503761/seg_08_narrator.mp3",
        "tokens": [
          {
            "surface": "She",
            "lemma": "she",
            "clickable": true,
            "token_idx": 0
          },
          {
            "surface": "gave",
            "lemma": "gave",
            "clickable": true,
            "token_idx": 1
          },
          {
            "surface": "Anna",
            "lemma": "anna",
            "clickable": true,
            "token_idx": 2
          },
          {
            "surface": "the",
            "lemma": "the",
            "clickable": true,
            "token_idx": 3
          },
          {
            "surface": "extra",
            "lemma": "extra",
            "clickable": true,
            "token_idx": 4
          },
          {
            "surface": "coin",
            "lemma": "coin",
            "clickable": true,
            "token_idx": 5
          },
          {
            "surface": "and",
            "lemma": "and",
            "clickable": true,
            "token_idx": 6
          },
          {
            "surface": "a",
            "lemma": "a",
            "clickable": true,
            "token_idx": 7
          },
          {
            "surface": "friendly",
            "lemma": "friendly",
            "clickable": true,
            "token_idx": 8
          },
          {
            "surface": "smile",
            "lemma": "smile",
            "clickable": true,
            "token_idx": 9
          },
          {
            "surface": ".",
            "lemma": ".",
            "clickable": false,
            "token_idx": 10
          }
        ]
      },
      {
        "segment_id": "s9",
        "speaker_id": "narrator",
        "voice_id": "en_narrator",
        "text": "Anna paid the two euros and thanked the vendor warmly.",
        "text_translation_ru": "Анна заплатила два евро и тепло поблагодарила продавца.",
        "audio_rel_path": "assets/reading/free_en_b1_reading_1778503761/seg_09_narrator.mp3",
        "tokens": [
          {
            "surface": "Anna",
            "lemma": "anna",
            "clickable": true,
            "token_idx": 0
          },
          {
            "surface": "paid",
            "lemma": "paid",
            "clickable": true,
            "token_idx": 1
          },
          {
            "surface": "the",
            "lemma": "the",
            "clickable": true,
            "token_idx": 2
          },
          {
            "surface": "two",
            "lemma": "two",
            "clickable": true,
            "token_idx": 3
          },
          {
            "surface": "euros",
            "lemma": "euros",
            "clickable": true,
            "token_idx": 4
          },
          {
            "surface": "and",
            "lemma": "and",
            "clickable": true,
            "token_idx": 5
          },
          {
            "surface": "thanked",
            "lemma": "thanked",
            "clickable": true,
            "token_idx": 6
          },
          {
            "surface": "the",
            "lemma": "the",
            "clickable": true,
            "token_idx": 7
          },
          {
            "surface": "vendor",
            "lemma": "vendor",
            "clickable": true,
            "token_idx": 8
          },
          {
            "surface": "warmly",
            "lemma": "warmly",
            "clickable": true,
            "token_idx": 9
          },
          {
            "surface": ".",
            "lemma": ".",
            "clickable": false,
            "token_idx": 10
          }
        ]
      },
      {
        "segment_id": "s10",
        "speaker_id": "narrator",
        "voice_id": "en_narrator",
        "text": "With the bowl in her bag, she walked away feeling happy.",
        "text_translation_ru": "С миской в сумке она ушла, чувствуя себя счастливой.",
        "audio_rel_path": "assets/reading/free_en_b1_reading_1778503761/seg_10_narrator.mp3",
        "tokens": [
          {
            "surface": "With",
            "lemma": "with",
            "clickable": true,
            "token_idx": 0
          },
          {
            "surface": "the",
            "lemma": "the",
            "clickable": true,
            "token_idx": 1
          },
          {
            "surface": "bowl",
            "lemma": "bowl",
            "clickable": true,
            "token_idx": 2
          },
          {
            "surface": "in",
            "lemma": "in",
            "clickable": true,
            "token_idx": 3
          },
          {
            "surface": "her",
            "lemma": "her",
            "clickable": true,
            "token_idx": 4
          },
          {
            "surface": "bag",
            "lemma": "bag",
            "clickable": true,
            "token_idx": 5
          },
          {
            "surface": ",",
            "lemma": ",",
            "clickable": false,
            "token_idx": 6
          },
          {
            "surface": "she",
            "lemma": "she",
            "clickable": true,
            "token_idx": 7
          },
          {
            "surface": "walked",
            "lemma": "walked",
            "clickable": true,
            "token_idx": 8
          },
          {
            "surface": "away",
            "lemma": "away",
            "clickable": true,
            "token_idx": 9
          },
          {
            "surface": "feeling",
            "lemma": "feeling",
            "clickable": true,
            "token_idx": 10
          },
          {
            "surface": "happy",
            "lemma": "happy",
            "clickable": true,
            "token_idx": 11
          },
          {
            "surface": ".",
            "lemma": ".",
            "clickable": false,
            "token_idx": 12
          }
        ]
      }
    ],
    "vocab_focus": [
      "market",
      "souvenir",
      "bowl",
      "vendor"
    ],
    "comprehension_questions": [
      {
        "id": "q1",
        "prompt": "Anna was looking for a souvenir in the market.",
        "type": "true_false",
        "correct_answer": "true",
        "explanation": "The text states: 'She was looking for a small souvenir to take home.'"
      },
      {
        "id": "q2",
        "prompt": "The bowl cost one euro.",
        "type": "true_false",
        "correct_answer": "false",
        "explanation": "The text says the price was two euros, not one."
      },
      {
        "id": "q3",
        "prompt": "Anna had only one euro coin when she tried to buy the bowl.",
        "type": "true_false",
        "correct_answer": "true",
        "explanation": "The text states: 'Anna only had one euro coin' for the two-euro bowl."
      }
    ]
  }
}
